tests/__init__.py
tests/test_xeger.py
xeger/__init__.py
xeger/__main__.py
xeger/xeger.py
xeger_lark-0.1.1.dist-info/LICENSE
xeger_lark-0.1.1.dist-info/METADATA
xeger_lark-0.1.1.dist-info/WHEEL
xeger_lark-0.1.1.dist-info/top_level.txt
xeger_lark-0.1.1.dist-info/RECORD
